explorer/__init__.py
explorer/auth.py
explorer/client.py
explorer/constants.py
explorer/dbapi.py
explorer/exceptions.py
explorer/logging.py
explorer/transaction.py
explorer/sqlalchemy/__init__.py
explorer/sqlalchemy/compiler.py
explorer/sqlalchemy/datatype.py
explorer/sqlalchemy/dialect.py
explorer/sqlalchemy/error.py
iq_explorer-0.313.0.dist-info/LICENSE
iq_explorer-0.313.0.dist-info/METADATA
iq_explorer-0.313.0.dist-info/WHEEL
iq_explorer-0.313.0.dist-info/entry_points.txt
iq_explorer-0.313.0.dist-info/top_level.txt
iq_explorer-0.313.0.dist-info/RECORD
