Metadata-Version: 2.1
Name: iq-explorer
Version: 0.313.0
Summary: Client for the Explorer distributed SQL Engine
Author: UST Explorer Team
Author-email: python-client@trino.io
License: Apache 2.0
Classifier: Development Status :: 4 - Beta
Classifier: Intended Audience :: Developers
Classifier: License :: OSI Approved :: Apache Software License
Classifier: Operating System :: MacOS :: MacOS X
Classifier: Operating System :: POSIX
Classifier: Operating System :: Microsoft :: Windows
Classifier: Programming Language :: Python
Classifier: Programming Language :: Python :: 3
Classifier: Programming Language :: Python :: 3.7
Classifier: Programming Language :: Python :: 3.8
Classifier: Programming Language :: Python :: 3.9
Classifier: Programming Language :: Python :: 3.10
Classifier: Programming Language :: Python :: Implementation :: CPython
Classifier: Programming Language :: Python :: Implementation :: PyPy
Classifier: Topic :: Database :: Front-Ends
Requires-Python: >=3.7
License-File: LICENSE
Requires-Dist: pytz
Requires-Dist: requests
Provides-Extra: all
Requires-Dist: requests-kerberos ; extra == 'all'
Requires-Dist: sqlalchemy (~=1.3) ; extra == 'all'
Provides-Extra: external-authentication-token-cache
Requires-Dist: keyring ; extra == 'external-authentication-token-cache'
Provides-Extra: kerberos
Requires-Dist: requests-kerberos ; extra == 'kerberos'
Provides-Extra: sqlalchemy
Requires-Dist: sqlalchemy (~=1.3) ; extra == 'sqlalchemy'
Provides-Extra: tests
Requires-Dist: requests-kerberos ; extra == 'tests'
Requires-Dist: sqlalchemy (~=1.3) ; extra == 'tests'
Requires-Dist: httpretty (<1.1) ; extra == 'tests'
Requires-Dist: pytest ; extra == 'tests'
Requires-Dist: pytest-runner ; extra == 'tests'
Requires-Dist: click ; extra == 'tests'
